{"Timestamp":"2024-06-15T23:16:18.9952623+07:00","Level":"Warning","MessageTemplate":"Unable to configure Browser Link script injection on the response. ","Properties":{"EventId":{"Id":3,"Name":"FailedToConfigureForBrowserLink"},"SourceContext":"Microsoft.WebTools.BrowserLink.Net.BrowserLinkMiddleware","RequestId":"0HN4DAO8KTR2T:00000001","RequestPath":"/classes/Edit/class/","ConnectionId":"0HN4DAO8KTR2T","MachineName":"ANITA-FIN-830","ProcessId":14164,"ThreadId":36}}
{"Timestamp":"2024-06-15T23:16:46.1167210+07:00","Level":"Warning","MessageTemplate":"Unable to configure Browser Link script injection on the response. ","Properties":{"EventId":{"Id":3,"Name":"FailedToConfigureForBrowserLink"},"SourceContext":"Microsoft.WebTools.BrowserLink.Net.BrowserLinkMiddleware","RequestId":"0HN4DAO8KTR30:00000001","RequestPath":"/model/create","ConnectionId":"0HN4DAO8KTR30","MachineName":"ANITA-FIN-830","ProcessId":14164,"ThreadId":8}}
